Metadata-Version: 2.1
Name: packaging-tutorial-Monica0-01
Version: 0.0.1
Summary: utils for myself
Home-page: https://github.com/pypa/sampleproject
Author: zhangzimei
Author-email: author@example.com
License: MIT
Platform: UNKNOWN
Classifier: Programming Language :: Python :: 3
Classifier: License :: OSI Approved :: MIT License
Classifier: Operating System :: OS Independent
Requires-Python: >=3.6
